readme.org
setup.py
pygass/__init__.py
pygass/constants.py
pygass/enhanced_ecommerce.py
pygass/helper.py
pygass/pygass.py
pygass/version.py
pygass.egg-info/PKG-INFO
pygass.egg-info/SOURCES.txt
pygass.egg-info/dependency_links.txt
pygass.egg-info/requires.txt
pygass.egg-info/top_level.txt
tests/__init__.py
tests/test_analytics.py
tests/test_enhanced_ecommerce.py
tests/test_helper.py