Metadata-Version: 2.1
Name: pygass
Version: 0.2.10
Summary: Server side implementation of Google Analytics in Python.
Home-page: https://gitlab.com/python-open-source-library-collection/pygass
Author: Oliver Marks
Author-email: oly@digitaloctave.com
License: GPL-3
Keywords: google analytics server side
Platform: UNKNOWN
Classifier: Intended Audience :: Developers
Classifier: License :: OSI Approved :: GNU General Public License v3 (GPLv3)
Classifier: Environment :: Web Environment
Classifier: Development Status :: 5 - Production/Stable
Classifier: Programming Language :: Python
Classifier: Operating System :: OS Independent
Classifier: Topic :: Software Development :: Libraries :: Python Modules
Classifier: Topic :: Internet
Classifier: Topic :: Internet :: WWW/HTTP
Classifier: Topic :: Internet :: WWW/HTTP :: WSGI
Requires: requests
